{
  "errors": {
    "news": [],
    "phemex": []
  },
  "generated_at": "2026-07-13T08:00:52+00:00",
  "headlines": [
    {
      "published": "Mon, 13 Jul 2026 05:29:39 +0000",
      "source": "Cointelegraph",
      "title": "Here\u2019s what happened in crypto today",
      "url": "https://cointelegraph.com/news/what-happened-in-crypto-today?utm_source=rss_feed&utm_medium=rss&utm_campaign=rss_partner_inbound"
    },
    {
      "published": "Mon, 13 Jul 2026 05:24:22 +0000",
      "source": "Cointelegraph",
      "title": "AI microbusinesses could drive $262B in stablecoin volume by 2033: Swyftx",
      "url": "https://cointelegraph.com/news/ai-enabled-businesses-freelancers-could-add-262b-in-stablecoin-volumes-swyftx?utm_source=rss_feed&utm_medium=rss&utm_campaign=rss_partner_inbound"
    },
    {
      "published": "Mon, 13 Jul 2026 04:43:50 +0000",
      "source": "Cointelegraph",
      "title": "Bank of Thailand targets USDT and cash flows in gray money crackdown",
      "url": "https://cointelegraph.com/news/thailand-targets-stablecoins-in-latest-laundering-crackdown?utm_source=rss_feed&utm_medium=rss&utm_campaign=rss_partner_inbound"
    },
    {
      "published": "Mon, 13 Jul 2026 01:49:17 +0000",
      "source": "Cointelegraph",
      "title": "Bitcoin ETFs draw $197M, snap 8-week outflow streak",
      "url": "https://cointelegraph.com/news/bitcoin-etfs-draw-197m-snap-8-week-outflow-streak?utm_source=rss_feed&utm_medium=rss&utm_campaign=rss_partner_inbound"
    },
    {
      "published": "Mon, 13 Jul 2026 03:22:28 -0400",
      "source": "The Block",
      "title": "Japan\u2019s SBI Group to launch JPYSC stablecoin lending service this month",
      "url": "https://www.theblock.co/post/407988/sbi-jpysc-stablecoin-lending?utm_source=rss&utm_medium=rss"
    },
    {
      "published": "Sun, 12 Jul 2026 23:59:28 -0400",
      "source": "The Block",
      "title": "Japan\u2019s Lawson convenience store pilots stablecoin payments with JPYC: report",
      "url": "https://www.theblock.co/post/407982/lawson-pilots-jpyc-stablecoin?utm_source=rss&utm_medium=rss"
    },
    {
      "published": "Sun, 12 Jul 2026 22:12:42 -0400",
      "source": "The Block",
      "title": "The Funding: Why Japan\u2019s SBI Holdings is investing big in crypto",
      "url": "https://www.theblock.co/post/407977/the-funding-why-japan-sbi-holdings-is-investing-big-in-crypto?utm_source=rss&utm_medium=rss"
    },
    {
      "published": "Sun, 12 Jul 2026 22:12:25 -0400",
      "source": "The Block",
      "title": "Bitcoin whale moves $188 million in BTC after seven-year dormancy: onchain data",
      "url": "https://www.theblock.co/post/407973/bitcoin-whale-moves-188-million-worth-btc?utm_source=rss&utm_medium=rss"
    }
  ],
  "phemex_watchlist": {
    "errors": [],
    "items": [
      {
        "change_pct": "-1.39%",
        "last_zone": "62.97K",
        "symbol": "BTCUSDT",
        "volume_band": "195.39M"
      },
      {
        "change_pct": "-0.59%",
        "last_zone": "1.79K",
        "symbol": "ETHUSDT",
        "volume_band": "42.16M"
      },
      {
        "change_pct": "-0.10%",
        "last_zone": "76.43",
        "symbol": "SOLUSDT",
        "volume_band": "35.27M"
      },
      {
        "change_pct": "-0.36%",
        "last_zone": "570.43",
        "symbol": "BNBUSDT",
        "volume_band": "30.57M"
      },
      {
        "change_pct": "-1.07%",
        "last_zone": "1.079",
        "symbol": "XRPUSDT",
        "volume_band": "16.02M"
      },
      {
        "change_pct": "+0.18%",
        "last_zone": "7.983",
        "symbol": "LINKUSDT",
        "volume_band": "13.90M"
      },
      {
        "change_pct": "-0.87%",
        "last_zone": "0.7322",
        "symbol": "SUIUSDT",
        "volume_band": "13.66M"
      },
      {
        "change_pct": "-1.96%",
        "last_zone": "0.1603",
        "symbol": "ADAUSDT",
        "volume_band": "8.88M"
      }
    ],
    "top_percentage_mover": {
      "change_pct": "+14.62%",
      "last_zone": "46.422",
      "symbol": "DEXEUSDT",
      "volume_band": "1.68M"
    },
    "top_volume_perp": {
      "change_pct": "-1.39%",
      "last_zone": "62.97K",
      "symbol": "BTCUSDT",
      "volume_band": "195.39M"
    }
  },
  "stance": "Neutral watch",
  "visibility": {
    "public": [
      "hourly stance",
      "headline titles and sources",
      "Phemex top volume perp",
      "Phemex top percentage mover",
      "watchlist symbols"
    ],
    "safety_note": "Broadcast is a watchlist and research feed only. It does not reveal private positions, sizes, balances, targets, or trade instructions.",
    "token_gated": [
      "headline history",
      "expanded watchlist",
      "strategy relevance notes",
      "portfolio overlap alerts"
    ]
  }
}
