{
  "delayed_fills": {
    "delay_hours": 72,
    "items": [],
    "note": "Delayed historical tape. Symbol, time, exchange, event, and rounded price zone only. No side, size, holdings, balances, targets, order IDs, or account identifiers."
  },
  "generated_at": "2026-07-08T00:00:54",
  "heartbeat": {
    "interval_minutes": 60,
    "last_run_at": "2026-07-08T00:00:02",
    "status": "Online"
  },
  "latest_recommendations": {
    "activity": {
      "Add": "High",
      "Hold": "High",
      "Pause Further Adds": "Low"
    },
    "event_mix": {
      "Ladder signal": 44,
      "Risk pause": 2,
      "Target stretch": 144
    },
    "mode": "Active management",
    "pressure_board": [
      {
        "heat": "High",
        "name": "Target stretch",
        "note": "Anonymized strategy cluster",
        "rank": "#1"
      },
      {
        "heat": "High",
        "name": "Ladder signal",
        "note": "Anonymized strategy cluster",
        "rank": "#2"
      },
      {
        "heat": "Low",
        "name": "Risk pause",
        "note": "Anonymized strategy cluster",
        "rank": "#3"
      }
    ],
    "tape": [],
    "timestamp": "2026-07-08T00:00:02"
  },
  "market_broadcast": {
    "errors": {
      "news": [],
      "phemex": []
    },
    "generated_at": "2026-07-08T04:00:53+00:00",
    "headlines": [
      {
        "published": "Wed, 08 Jul 2026 03:25:30 +0000",
        "source": "Cointelegraph",
        "title": "CFTC charges commodity, crypto pool operator with $14M fraud",
        "url": "https://cointelegraph.com/news/cftc-charges-commodity-crypto-pool-operator-with-14m-fraud?utm_source=rss_feed&utm_medium=rss&utm_campaign=rss_partner_inbound"
      },
      {
        "published": "Wed, 08 Jul 2026 02:40:13 +0000",
        "source": "Cointelegraph",
        "title": "Strike launches \u2018volatility-proof\u2019 Bitcoin loans amid bear market, but at a cost",
        "url": "https://cointelegraph.com/news/strike-launches-volatility-proof-bitcoin-loans-amid-bear-market-but-at-what-cost?utm_source=rss_feed&utm_medium=rss&utm_campaign=rss_partner_inbound"
      },
      {
        "published": "Tue, 07 Jul 2026 21:39:48 +0000",
        "source": "Cointelegraph",
        "title": "SEC crypto rule changes are high on its 2026 agenda",
        "url": "https://cointelegraph.com/news/sec-crypto-rule-changes-2026-agenda?utm_source=rss_feed&utm_medium=rss&utm_campaign=rss_partner_inbound"
      },
      {
        "published": "Tue, 07 Jul 2026 21:14:37 +0000",
        "source": "Cointelegraph",
        "title": "Ether climbs toward $2K as Bitmine buys ETH, Robinhood L2 boost",
        "url": "https://cointelegraph.com/markets/ether-climbs-toward-2k-as-bitmine-buys-eth-robinhood-l2-boost?utm_source=rss_feed&utm_medium=rss&utm_campaign=rss_partner_inbound"
      },
      {
        "published": "Tue, 07 Jul 2026 17:30:10 -0400",
        "source": "The Block",
        "title": "Kraken wins $22 million arbitration against auditor Mazars for ditching the firm during Operation Choke Point 2.0",
        "url": "https://www.theblock.co/post/407524/kraken-wins-22-million-arbitration-auditor-mazars-for-ditching-during-operation-choke-point-2-0?utm_source=rss&utm_medium=rss"
      },
      {
        "published": "Tue, 07 Jul 2026 16:58:49 -0400",
        "source": "The Block",
        "title": "CFTC charges North Carolina man over alleged $14 million crypto, futures fraud",
        "url": "https://www.theblock.co/post/407516/cftc-charges-north-carolina-man-alleged-14-million-crypto-futures-fraud?utm_source=rss&utm_medium=rss"
      },
      {
        "published": "Tue, 07 Jul 2026 16:48:00 -0400",
        "source": "The Block",
        "title": "Jack Mallers\u2019 Strike launches \u2018volatility-proof\u2019 bitcoin loans built to protect against liquidation",
        "url": "https://www.theblock.co/post/407511/jack-maller-strike-launches-volatility-proof-bitcoin-loans-protect-against-liquidation?utm_source=rss&utm_medium=rss"
      },
      {
        "published": "Tue, 07 Jul 2026 14:12:51 -0400",
        "source": "The Block",
        "title": "ZEC jumps 12% as Zcash nears mathematical proof against hidden counterfeit bugs",
        "url": "https://www.theblock.co/post/407495/zec-price-jumps-zcash-nears-mathematical-proof-hidden-counterfeit-bugs?utm_source=rss&utm_medium=rss"
      }
    ],
    "phemex_watchlist": {
      "errors": [],
      "items": [
        {
          "change_pct": "-0.75%",
          "last_zone": "62.72K",
          "symbol": "BTCUSDT",
          "volume_band": "270.76M"
        },
        {
          "change_pct": "-1.16%",
          "last_zone": "1.75K",
          "symbol": "ETHUSDT",
          "volume_band": "65.06M"
        },
        {
          "change_pct": "-2.94%",
          "last_zone": "78.65",
          "symbol": "SOLUSDT",
          "volume_band": "56.19M"
        },
        {
          "change_pct": "-1.86%",
          "last_zone": "568.86",
          "symbol": "BNBUSDT",
          "volume_band": "32.44M"
        },
        {
          "change_pct": "-2.51%",
          "last_zone": "7.683",
          "symbol": "LINKUSDT",
          "volume_band": "18.44M"
        },
        {
          "change_pct": "-3.06%",
          "last_zone": "0.7124",
          "symbol": "SUIUSDT",
          "volume_band": "17.29M"
        },
        {
          "change_pct": "-3.02%",
          "last_zone": "1.0942",
          "symbol": "XRPUSDT",
          "volume_band": "15.66M"
        },
        {
          "change_pct": "-5.75%",
          "last_zone": "0.1705",
          "symbol": "ADAUSDT",
          "volume_band": "14.35M"
        }
      ],
      "top_percentage_mover": {
        "change_pct": "-76.09%",
        "last_zone": "3.297",
        "symbol": "LABUSDT",
        "volume_band": "1.07M"
      },
      "top_volume_perp": {
        "change_pct": "-0.75%",
        "last_zone": "62.72K",
        "symbol": "BTCUSDT",
        "volume_band": "270.76M"
      }
    },
    "stance": "Defensive watch",
    "visibility": {
      "public": [
        "hourly stance",
        "headline titles and sources",
        "Phemex top volume perp",
        "Phemex top percentage mover",
        "watchlist symbols"
      ],
      "safety_note": "Broadcast is a watchlist and research feed only. It does not reveal private positions, sizes, balances, targets, or trade instructions.",
      "token_gated": [
        "headline history",
        "expanded watchlist",
        "strategy relevance notes",
        "portfolio overlap alerts"
      ]
    }
  },
  "performance_chart": [
    {
      "band": "Near origin",
      "closed_pct": 6.9,
      "name": "Phemex",
      "open_pct": -5.9,
      "total_pct": 1.0
    },
    {
      "band": "Ahead",
      "closed_pct": 8.7,
      "name": "ApeX",
      "open_pct": 0.0,
      "total_pct": 8.7
    }
  ],
  "pulse": {
    "activity": 84,
    "performance_pressure": 71,
    "survival_floor": 90,
    "target_cleanliness": 77,
    "trinity": 81
  },
  "pulse_equations": {
    "activity": "A = strategy activity band",
    "performance_pressure": "P = avg(exchange performance bands)",
    "survival_floor": "S = avg(exchange add-capacity bands)",
    "target_cleanliness": "T = avg(exchange target-health bands)",
    "trinity": "0.30T + 0.30S + 0.20P + 0.20A"
  },
  "solspot": {
    "actions": [
      {
        "action": "SOL -> JTO",
        "signature": "jjQxAcWD48ZEkVziEBizwo1oP1iJHSqQxnQLzRJxN6EvYt9Vu3yfuKQ8T717Nzzn9YufZJo49tyGQ48VBcvGsTS",
        "solscan": "https://solscan.io/tx/jjQxAcWD48ZEkVziEBizwo1oP1iJHSqQxnQLzRJxN6EvYt9Vu3yfuKQ8T717Nzzn9YufZJo49tyGQ48VBcvGsTS",
        "spent_sol": "0.003",
        "time": "2026-07-08T01:40:44.829Z"
      },
      {
        "action": "SOL -> JUP",
        "signature": "63RcNQK1oy7yyvZw2aqUFUqfFJ48zXVm5HnE9arYoUXdRQPMPgD1vSGSbTf2TVd9GMwi7NSZQVvU9KKkdAMx9Lc1",
        "solscan": "https://solscan.io/tx/63RcNQK1oy7yyvZw2aqUFUqfFJ48zXVm5HnE9arYoUXdRQPMPgD1vSGSbTf2TVd9GMwi7NSZQVvU9KKkdAMx9Lc1",
        "spent_sol": "0.003",
        "time": "2026-07-08T01:33:21.980Z"
      },
      {
        "action": "SOL -> 1 USDC",
        "signature": "51v6CSS9X2tgrBYvmX7HkZhrgR66TMrNaHzFjHtbyUWX2zVE9qNHzB4jZUrTjArF4rbUpr4wb24S2ETipVKG4qKH",
        "solscan": "https://solscan.io/tx/51v6CSS9X2tgrBYvmX7HkZhrgR66TMrNaHzFjHtbyUWX2zVE9qNHzB4jZUrTjArF4rbUpr4wb24S2ETipVKG4qKH",
        "spent_sol": "0.012501",
        "time": "2026-07-08T01:30:43.257Z"
      }
    ],
    "approved": [
      "JUP",
      "JTO"
    ],
    "auto_sign": true,
    "balances": [
      {
        "amount": "0.044254",
        "role": "gas and opportunity reserve",
        "symbol": "SOL"
      },
      {
        "amount": "1",
        "role": "defensive reserve",
        "symbol": "USDC"
      },
      {
        "amount": "0.999924",
        "role": "Solana DeFi infrastructure exposure",
        "symbol": "JUP"
      },
      {
        "amount": "0.326333",
        "role": "Solana staking and validator infrastructure exposure",
        "symbol": "JTO"
      }
    ],
    "daily_limit_sol": 1,
    "daily_spent_sol": "0.018501",
    "generated_at": "2026-07-08T03:43:06.663Z",
    "latest_execution": {
      "action": "",
      "attempted": false,
      "reason": "",
      "signature": "",
      "solscan": ""
    },
    "manual_confirm_required": false,
    "max_swap_sol": 0.25,
    "mode": "auto_live",
    "recommendation": {
      "action": "Watch",
      "reason": "USDC reserve exists; JUP/JTO routes available for manual tiny-add review."
    },
    "rotation": {
      "candidates": [
        {
          "dex_url": "https://dexscreener.com/solana/gdc11vqjfq6isptw1avoqowxnd7eq3jetjwh1ltt4qt8",
          "liquidity": "125489",
          "route": "Route OK",
          "score": 367.62,
          "status": "candidate_only",
          "symbol": "tolywifhat",
          "volume_1h": "360721",
          "volume_24h": "2963485"
        },
        {
          "dex_url": "https://dexscreener.com/solana/6adx5qhm4iwee39nik8cambb3sjdgslw7vgpomy2vqwz",
          "liquidity": "89387",
          "route": "Route OK",
          "score": 350.26,
          "status": "candidate_only",
          "symbol": "MASON",
          "volume_1h": "478035",
          "volume_24h": "1794638"
        },
        {
          "dex_url": "https://dexscreener.com/solana/6mc6txdrckl1mhr8s9kys55cchkdzx3ayianas6aa9ym",
          "liquidity": "132142",
          "route": "Candidate only",
          "score": 347.87,
          "status": "candidate_only",
          "symbol": "BULLSEY",
          "volume_1h": "496583",
          "volume_24h": "2251633"
        },
        {
          "dex_url": "https://dexscreener.com/solana/8yvumppwyjzqhsr2b5muoulugj8grusqm7yddswthgju",
          "liquidity": "96972",
          "route": "Route OK",
          "score": 339.75,
          "status": "candidate_only",
          "symbol": "DONALT",
          "volume_1h": "160710",
          "volume_24h": "2402837"
        },
        {
          "dex_url": "https://dexscreener.com/solana/4dtppur4cp7eksn57bs2cnxay3e98fjtz5kce8v5juu2",
          "liquidity": "30235",
          "route": "Route OK",
          "score": 326.77,
          "status": "candidate_only",
          "symbol": "BabyCupsey",
          "volume_1h": "67233",
          "volume_24h": "1385383"
        },
        {
          "dex_url": "https://dexscreener.com/solana/5smcocy9fvw3g1apyzyhxd2ozyasewkozjmtgsphjsjg",
          "liquidity": "84680",
          "route": "Route OK",
          "score": 318.32,
          "status": "candidate_only",
          "symbol": "SUNUSI",
          "volume_1h": "18638",
          "volume_24h": "3021895"
        },
        {
          "dex_url": "https://dexscreener.com/solana/4lxumvpxvhdeac3c2lvjj9kgmu94pyv4inflhcqc6lit",
          "liquidity": "58506",
          "route": "Route OK",
          "score": 306.76,
          "status": "candidate_only",
          "symbol": "ANSEMIUS",
          "volume_1h": "19087",
          "volume_24h": "2647865"
        },
        {
          "dex_url": "https://dexscreener.com/solana/a5ifvpu2th27kfgzuhwswforizskkzyfvhv5rmqg85bw",
          "liquidity": "11752",
          "route": "Route OK",
          "score": 293.33,
          "status": "candidate_only",
          "symbol": "WhiteWhale",
          "volume_1h": "24990",
          "volume_24h": "423592"
        }
      ],
      "filters": {
        "min_liquidity_usd": 10000,
        "min_volume_24h_usd": 25000,
        "quote_sol": 0.001,
        "scan_limit": 20
      },
      "generated_at": "2026-07-08T03:43:06.486Z",
      "mode": "candidate scan only; candidates are not auto-tradable until promoted"
    },
    "wallet": "2Lv7...UzA2",
    "wallet_public": "2Lv7sFd974NszRt7ZciqyuaDBdoDdgshTofez1yYUzA2",
    "watch_only": [
      "HedgAI",
      "BONK",
      "WIF"
    ]
  },
  "strategy": {
    "current_focus": "Building a public-safe view into the Trinity financial operating system: strategy, risk posture, target health, and anonymized activity.",
    "name": "Trinity Trading System",
    "public_note": "Public-safe operating view. Performance is shown as percentages and bands. Delayed historical fills may show symbol, time, and rounded price zone only. No side, balances, holdings, order size, next targets, API keys, or account identifiers are published."
  },
  "systems": {
    "apex": {
      "automation": "Read/hold monitoring",
      "connection": "Online",
      "free_capital": "Healthy",
      "performance": "Ahead",
      "risk_mode": "Normal",
      "role": "Futures-capable rotation book, currently long-only",
      "strategy_type": "Configured long-only; shorts possible by future strategy update",
      "target_health": "Clean"
    },
    "onchain": {
      "automation": "Auto-live under cap",
      "connection": "Auto-live",
      "free_capital": "Small test wallet",
      "performance": "Active proof + rotation",
      "risk_mode": "Under 1 SOL cap",
      "role": "Solana spot reserve and rotation wallet",
      "strategy_type": "Long-only spot; no shorts, no perps",
      "target_health": "Route-gated"
    },
    "phemex": {
      "automation": "Hourly review active",
      "connection": "Online",
      "free_capital": "Healthy",
      "performance": "Near origin",
      "risk_mode": "Normal",
      "role": "Same-symbol long/short hedge-mode volatility book",
      "strategy_type": "Long and short can run on the same symbol",
      "target_health": "Repairing"
    }
  }
}
