{
  "ai_tokens_used": 0,
  "changed": true,
  "events": [
    {
      "event": "Target repair logged",
      "exchange": "Phemex",
      "id": "607921a98ddac4d7",
      "price_zone": "near 0.027",
      "reason_category": "target maintenance",
      "status": "submitted",
      "symbol": "BIOUSDT",
      "time": "2026-07-24T17:27"
    },
    {
      "event": "Target repair logged",
      "exchange": "Phemex",
      "id": "b7e8539af155a2da",
      "price_zone": "near 0.087",
      "reason_category": "target maintenance",
      "status": "submitted",
      "symbol": "ALGOUSDT",
      "time": "2026-07-24T17:27"
    },
    {
      "event": "Target repair logged",
      "exchange": "Phemex",
      "id": "ab19a9f7edcbd4d1",
      "price_zone": "near 0.061",
      "reason_category": "target maintenance",
      "status": "submitted",
      "symbol": "AUSDT",
      "time": "2026-07-24T17:27"
    },
    {
      "event": "Target repair logged",
      "exchange": "Phemex",
      "id": "f6e837742ef92b8e",
      "price_zone": "near 0.044",
      "reason_category": "target maintenance",
      "status": "submitted",
      "symbol": "SEIUSDT",
      "time": "2026-07-24T17:27"
    },
    {
      "event": "Profit target moved",
      "exchange": "Phemex",
      "id": "72758cf3e593e24c",
      "price_zone": "near 0.048",
      "reason_category": "strategy maintenance",
      "status": "submitted",
      "symbol": "SEIUSDT",
      "time": "2026-07-24T16:27"
    },
    {
      "event": "Ladder add logged",
      "exchange": "Phemex",
      "id": "9dae359292fca745",
      "price_zone": "near 0.045",
      "reason_category": "ladder rule",
      "status": "submitted",
      "symbol": "SEIUSDT",
      "time": "2026-07-24T16:27"
    },
    {
      "event": "Target repair logged",
      "exchange": "Phemex",
      "id": "dca3cd51e58d95ee",
      "price_zone": "micro-price zone",
      "reason_category": "target maintenance",
      "status": "submitted",
      "symbol": "HOMEUSDT",
      "time": "2026-07-24T16:27"
    },
    {
      "event": "Target repair logged",
      "exchange": "Phemex",
      "id": "4eb92529a0f1e491",
      "price_zone": "near 0.142",
      "reason_category": "target maintenance",
      "status": "submitted",
      "symbol": "APEUSDT",
      "time": "2026-07-24T15:27"
    },
    {
      "event": "Target repair logged",
      "exchange": "Phemex",
      "id": "68840444b11eac68",
      "price_zone": "near 1.1",
      "reason_category": "target maintenance",
      "status": "submitted",
      "symbol": "XRPUSDT",
      "time": "2026-07-24T15:27"
    },
    {
      "event": "Target repair logged",
      "exchange": "Phemex",
      "id": "78edc166ea1cea1e",
      "price_zone": "near 0.034",
      "reason_category": "target maintenance",
      "status": "submitted",
      "symbol": "TNSRUSDT",
      "time": "2026-07-24T15:27"
    },
    {
      "event": "Profit target moved",
      "exchange": "Phemex",
      "id": "50df23aaba74a87a",
      "price_zone": "near 0.621",
      "reason_category": "strategy maintenance",
      "status": "submitted",
      "symbol": "JTOUSDT",
      "time": "2026-07-24T14:27"
    },
    {
      "event": "Ladder add logged",
      "exchange": "Phemex",
      "id": "c948a6d81dc7e370",
      "price_zone": "near 0.584",
      "reason_category": "ladder rule",
      "status": "submitted",
      "symbol": "JTOUSDT",
      "time": "2026-07-24T14:27"
    },
    {
      "event": "Profit target moved",
      "exchange": "Phemex",
      "id": "2d6ec338e3d2ad16",
      "price_zone": "micro-price zone",
      "reason_category": "strategy maintenance",
      "status": "submitted",
      "symbol": "WUSDT",
      "time": "2026-07-24T14:27"
    },
    {
      "event": "Ladder add logged",
      "exchange": "Phemex",
      "id": "dde2d62b80e86482",
      "price_zone": "micro-price zone",
      "reason_category": "ladder rule",
      "status": "submitted",
      "symbol": "WUSDT",
      "time": "2026-07-24T14:27"
    },
    {
      "event": "Target repair logged",
      "exchange": "Phemex",
      "id": "f610188e7d8d4290",
      "price_zone": "near 0.061",
      "reason_category": "target maintenance",
      "status": "submitted",
      "symbol": "HYPERUSDT",
      "time": "2026-07-24T14:27"
    },
    {
      "event": "Target repair logged",
      "exchange": "Phemex",
      "id": "2a355cc98b24e4d5",
      "price_zone": "near 0.177",
      "reason_category": "target maintenance",
      "status": "submitted",
      "symbol": "XLMUSDT",
      "time": "2026-07-24T14:27"
    },
    {
      "event": "Target repair logged",
      "exchange": "Phemex",
      "id": "d7392340f6ae2c4b",
      "price_zone": "near 0.034",
      "reason_category": "target maintenance",
      "status": "submitted",
      "symbol": "TNSRUSDT",
      "time": "2026-07-24T14:27"
    },
    {
      "event": "Target repair logged",
      "exchange": "Phemex",
      "id": "ac3da075ac095af5",
      "price_zone": "near 0.579",
      "reason_category": "target maintenance",
      "status": "submitted",
      "symbol": "JTOUSDT",
      "time": "2026-07-24T14:27"
    },
    {
      "event": "Target repair logged",
      "exchange": "Phemex",
      "id": "1ee17c0e7e5a6603",
      "price_zone": "near 0.061",
      "reason_category": "target maintenance",
      "status": "submitted",
      "symbol": "OPNUSDT",
      "time": "2026-07-24T13:27"
    },
    {
      "event": "Target repair logged",
      "exchange": "Phemex",
      "id": "c17c6b78c5a14665",
      "price_zone": "micro-price zone",
      "reason_category": "target maintenance",
      "status": "submitted",
      "symbol": "ZKUSDT",
      "time": "2026-07-24T13:27"
    },
    {
      "event": "Target repair logged",
      "exchange": "Phemex",
      "id": "c0f89d9e8eeb537d",
      "price_zone": "micro-price zone",
      "reason_category": "target maintenance",
      "status": "submitted",
      "symbol": "GPSUSDT",
      "time": "2026-07-24T13:27"
    },
    {
      "event": "Target repair logged",
      "exchange": "Phemex",
      "id": "ae0486bdfb73e2c8",
      "price_zone": "micro-price zone",
      "reason_category": "target maintenance",
      "status": "submitted",
      "symbol": "ZORAUSDT",
      "time": "2026-07-24T13:27"
    },
    {
      "event": "Target repair logged",
      "exchange": "Phemex",
      "id": "88a7b01cde80e1d2",
      "price_zone": "micro-price zone",
      "reason_category": "target maintenance",
      "status": "submitted",
      "symbol": "u1000PEPEUSDT",
      "time": "2026-07-24T13:27"
    },
    {
      "event": "Target repair logged",
      "exchange": "Phemex",
      "id": "ad9c75a55dcbf942",
      "price_zone": "near 0.034",
      "reason_category": "target maintenance",
      "status": "submitted",
      "symbol": "TNSRUSDT",
      "time": "2026-07-24T13:27"
    },
    {
      "event": "Target repair logged",
      "exchange": "Phemex",
      "id": "c632f706e0154dd1",
      "price_zone": "near 0.061",
      "reason_category": "target maintenance",
      "status": "submitted",
      "symbol": "OPNUSDT",
      "time": "2026-07-24T12:27"
    },
    {
      "event": "Target repair logged",
      "exchange": "Phemex",
      "id": "98d4c5a1a15f8b3c",
      "price_zone": "micro-price zone",
      "reason_category": "target maintenance",
      "status": "submitted",
      "symbol": "ZKUSDT",
      "time": "2026-07-24T12:27"
    },
    {
      "event": "Target repair logged",
      "exchange": "Phemex",
      "id": "fc5bcc917f611ce7",
      "price_zone": "micro-price zone",
      "reason_category": "target maintenance",
      "status": "submitted",
      "symbol": "GPSUSDT",
      "time": "2026-07-24T12:27"
    },
    {
      "event": "Target repair logged",
      "exchange": "Phemex",
      "id": "e23f4facfbf01d25",
      "price_zone": "near 0.175",
      "reason_category": "target maintenance",
      "status": "submitted",
      "symbol": "BERAUSDT",
      "time": "2026-07-24T12:27"
    },
    {
      "event": "Target repair logged",
      "exchange": "Phemex",
      "id": "6935eda2ea853370",
      "price_zone": "near 0.117",
      "reason_category": "target maintenance",
      "status": "submitted",
      "symbol": "CCUSDT",
      "time": "2026-07-24T12:27"
    },
    {
      "event": "Target repair logged",
      "exchange": "Phemex",
      "id": "94ca23c6aa8edad8",
      "price_zone": "micro-price zone",
      "reason_category": "target maintenance",
      "status": "submitted",
      "symbol": "ZORAUSDT",
      "time": "2026-07-24T12:27"
    }
  ],
  "generated_at": "2026-07-24T21:29:32Z",
  "latest_event_id": "607921a98ddac4d7",
  "mode": "deterministic_log_watcher",
  "poll_interval_minutes": 5,
  "safety_note": "Five-minute public event feed. No AI call, no balances, no holdings, no sizes, no side, no order IDs, no next targets, and no account identifiers."
}
